[
  {
    "id": 1,
    "title": "Mill Financial Group - Web app",
    "category" : "Web Development",
    "url": "https://millfinancialgroup.com",
    "thumbnail": "images/mill_intranet_portada.jpg",
    "description": "<p>This is an web app developed for the insurance company Mill Financial Group. The goal was to create a tool which the insurance agents could use to make easier their job; in the app they can manage their meetings, and receive automated reminders, with their clients, have a contact list of them and register their sales to get paid their commission</p>"
      "width": "col-md-7",
      "wrap": false,
      "height": "img-2"
    },
    "tags": [
      "PHP", "MVC", "MySQL", "HTML 5", "CSS 3", "JavaScript", "Bootstrap"
    ],
    "gallery": [
      "data/projects/1/mill_intranet_portada.jpg",
      "data/projects/1/mill-login.PNG",
      "data/projects/1/mill-dashboard.png",
      "data/projects/1/diary_visit.png",
      "data/projects/1/contact_download_modules.png",
      "data/projects/1/sales_diary_modules.png",
      "data/projects/1/tablet_contact_list.png",
      "data/projects/1/tablet_diary.png"
    ]
  },
  {
    "id": 2,
    "title": "Tumaca - Website",
    "category" : "Web Design",
    "url": "http://tumaca7.com",
    "thumbnail": "images/tumaca-portada.jpg",
    "layout": {
      "width": "col-md-12",
      "wrap": "col-md-5",
      "wrapType": "opening",
      "height": "img"
    },
    "description": "<p>With the design made by <a href='https://www.behance.net/AdrianaVillegas93' target='_blank'>Adriana</a>, I created a fast and fully responsive website for Tumaca, to show their services and products</p>",
    "tags": ["HTML 5", "CSS 3", "JavaScript", "jQuery", "Materialize-css"],
    "gallery": [
      "data/projects/2/tumaca-portada.jpg",
      "data/projects/2/web-tumaca.jpg",
      "data/projects/2/tablet.png",
      "data/projects/2/scroll.png",
      "data/projects/2/scroll_2.png",
      "data/projects/2/web-refrigerante-super-duty.jpg"
    ]
  },
  {
    "id": 3,
    "title": "Mill Financial Group - Website",
    "category" : "Web Design",
    "url": "https://millfinancialgroup.com",
    "thumbnail": "images/mill_portada.jpg",
    "layout": {
      "width": "col-md-12",
      "wrap": "col-md-5",
      "wrapType": "closing",
      "height": "img"
    },
    "description": "<p>Back with the insurance company Mill Financial Group, we created and modern design style website, to show the goals and information of the company</p>",
    "tags": ["HTML 5", "CSS 3", "Materialize-css", "OwlCarousel.js", "jQuery", "JavaScript"],
    "gallery": [
      "data/projects/3/mill_portada.jpg",
      "data/projects/3/mill-home.JPG",
      "data/projects/3/mill_about.png",
      "data/projects/3/screen_phon4.png",
      "data/projects/3/mill_home_2.png",
      "data/projects/3/mill_mobile.JPG"
    ]
  },
  {
    "id": 4,
    "title": "Senepol Norte Sur - WordPress Website",
    "category": "WordPress Development",
    "url": "http://senepolnortesur.com",
    "thumbnail": "images/senepol_portada.jpg",
    "layout": {
      "width": "col-md-4",
      "wrap": false,
      "height": "img"
    },
    "description": "<p>Senepol Norte Sur is a company of cattle, specialized on Senepol cow race. They wanted to create an online catalog where they could show their animals to their clients</p>",
    "tags": ["PHP", "HTML 5", "JavaScript", "jQuery", "WordPress"],
    "gallery": [
      "data/projects/4/home-1.PNG",
      "data/projects/4/whole_page.png",
      "data/projects/4/single_vaca.png",
      "data/projects/4/tv_vacas.png",
      "data/projects/4/productos.png",
      "data/projects/4/table_view_cavacas.png"
    ]
  },
  {
    "id": 5,
    "title": "Dupar - WordPress Website",
    "category": "WordPress Development",
    "url": "http://dupar.com.ve",
    "thumbnail": "images/dupar_portada.jpg",
    "layout": {
      "width": "col-md-8",
      "wrap": false,
      "height": "img"
    },
    "description": "<p>Website created for the industrial products manufacturer Dupar.</p>",
    "tags": ["WordPress"],
    "gallery": [
      "data/projects/5/dupar_home-1.PNG",
      "data/projects/5/dupar_home-2.PNG",
      "data/projects/5/dupar_producto.jpg",
      "data/projects/5/dupar_producto-1.PNG",
      "data/projects/5/dupar_responsive-1.PNG",
      "data/projects/5/dupar_captura-dupar_2.PNG"
    ]
  }
]